quranallsbuforuni/__init__.py
quranallsbuforuni/module1.py
quranallsbuforuni/module2.py
Quran_sureh1-1.dist-info/METADATA
Quran_sureh1-1.dist-info/WHEEL
Quran_sureh1-1.dist-info/top_level.txt
Quran_sureh1-1.dist-info/RECORD
