Metadata-Version: 2.1
Name: Quran-sureh1
Version: 1
Summary: Quran_sureh1
Author: Masoud Shafiei
Author-email: masoudshafiei89@yahoo.com
Keywords: quran,sureh1
Classifier: Programming Language :: Python :: 3
